targer_api/__init__.py
targer_api/api.py
targer_api/constants.py
targer_api/model.py
targer_api/parse.py
targer_api-1.1.1.dist-info/LICENSE
targer_api-1.1.1.dist-info/METADATA
targer_api-1.1.1.dist-info/WHEEL
targer_api-1.1.1.dist-info/top_level.txt
targer_api-1.1.1.dist-info/RECORD
