Metadata-Version: 2.1
Name: targer-api
Version: 1.1.1
Summary: Simple, type-safe access to the TARGER neural argument tagging APIs.
Author-email: Jan Heinrich Reimer <heinrich.reimer@uni-jena.de>
Project-URL: Homepage, https://github.com/webis-de/targer-api
Project-URL: Bug Tracker, https://github.com/webis-de/targer-api/issues
Classifier: Programming Language :: Python :: 3
Classifier: Programming Language :: Python :: 3 :: Only
Classifier: Programming Language :: Python :: 3.7
Classifier: Programming Language :: Python :: 3.8
Classifier: Programming Language :: Python :: 3.9
Classifier: Programming Language :: Python :: 3.10
Classifier: Programming Language :: Python :: 3.11
Classifier: License :: OSI Approved :: MIT License
Classifier: Operating System :: OS Independent
Classifier: Intended Audience :: Science/Research
Classifier: Topic :: Scientific/Engineering
Requires-Python: >=3.7
License-File: LICENSE
Requires-Dist: diskcache ~=5.4
Requires-Dist: importlib-metadata ~=4.0
Requires-Dist: requests ~=2.26
Provides-Extra: test
Requires-Dist: flake8 ~=5.0 ; extra == 'test'
Requires-Dist: pylint ~=2.12 ; extra == 'test'
Requires-Dist: pytest ~=7.2 ; extra == 'test'
Requires-Dist: pytest-cov ~=4.0 ; extra == 'test'
